reddack/__init__.py
reddack/__main__.py
reddack/cli.py
reddack/config.py
reddack/exceptions.py
reddack/models.py
reddack/payload.py
reddack/slack.py
reddack/utils.py
reddack-0.1.7.dist-info/LICENSE
reddack-0.1.7.dist-info/METADATA
reddack-0.1.7.dist-info/WHEEL
reddack-0.1.7.dist-info/top_level.txt
reddack-0.1.7.dist-info/RECORD
